LICENSE
MANIFEST.in
README.md
setup.py
libpythonpro_urbanstech/__init__.py
libpythonpro_urbanstech/github_api.py
libpythonpro_urbanstech.egg-info/PKG-INFO
libpythonpro_urbanstech.egg-info/SOURCES.txt
libpythonpro_urbanstech.egg-info/dependency_links.txt
libpythonpro_urbanstech.egg-info/not-zip-safe
libpythonpro_urbanstech.egg-info/requires.txt
libpythonpro_urbanstech.egg-info/top_level.txt